{
  "name": "Asalto mental",
  "type": "poder",
  "_id": "iEiGrH45Iy8lTpcq",
  "img": "icons/svg/item-bag.svg",
  "system": {
    "descripcion": "Sobrecarga sensorial: -1D a acciones, -1 Salud, -3 a Agilidad/Aplomo/Perspicacia. Uso agresivo no defensivo sobre una persona obliga al psíquico a tirada de pánico gravedad 3.\n\nActivación: 1 turno completo. Duración: 3 turnos. No se puede lanzar de nuevo sobre víctima ya afectada hasta que acabe. Coste: 4 poder + 5 poder.",
    "tipo": "Poder de médium",
    "habilidad": "cultura",
    "atributo": "int",
    "dificultad": 12,
    "preparacion": "",
    "lanzamiento": "",
    "duracion": "Activación: 1 turno completo. Duración: 3 turnos. No se puede lanzar de nuevo sobre víctima ya afectada hasta que acabe. Coste: 4 poder + 5 poder.",
    "caducidad": "",
    "equipado": false,
    "automatismo": ""
  },
  "effects": [],
  "folder": null,
  "sort": 100000,
  "ownership": {
    "default": 2
  },
  "flags": {},
  "_stats": {
    "compendiumSource": null,
    "duplicateSource": null,
    "exportSource": null,
    "coreVersion": "13.351",
    "systemId": "ysystem3-srd",
    "systemVersion": "0.3.8",
    "createdTime": 1779666008608,
    "modifiedTime": 1779666008608,
    "lastModifiedBy": null
  }
}
